nonebot_plugin_apod/__init__.py
nonebot_plugin_apod/apod.py
nonebot_plugin_apod/config.py
nonebot_plugin_apod/css/dark.css
nonebot_plugin_apod/css/light.css
nonebot_plugin_apod/infopuzzle.py
nonebot_plugin_apod-1.0.8.dist-info/WHEEL
nonebot_plugin_apod-1.0.8.dist-info/METADATA
nonebot_plugin_apod-1.0.8.dist-info/RECORD
