Metadata-Version: 2.4
Name: nonebot-plugin-apod
Version: 1.0.8
Summary: 定时发送 NASA 每日提供的天文图片
Keywords: nonebot2,NASA
Author: lyqgzbl
Author-email: lyqgzbl <admin@lyqgzbl.com>
License-Expression: MIT
Requires-Dist: nonebot2>=2.2.1,<3.0.0
Requires-Dist: httpx>=0.28.0,<1.0.0
Requires-Dist: nonebot-plugin-argot>=0.2.2
Requires-Dist: nonebot-plugin-localstore>=0.7.0,<1.0.0
Requires-Dist: nonebot-plugin-apscheduler>=0.5.0,<1.0.0
Requires-Dist: nonebot-plugin-alconna>=0.57.1,<1.0.0
Requires-Dist: nonebot-plugin-htmlrender>=0.5.0,<1.0.0
Requires-Python: >=3.10
Project-URL: Documentation, https://github.com/lyqgzbl/nonebot-plugin-apod#readme
Project-URL: Homepage, https://github.com/lyqgzbl/nonebot-plugin-apod
Project-URL: Repository, https://github.com/lyqgzbl/nonebot-plugin-apod
